ovpn3.py
ovpn3-0.1.3.dist-info/entry_points.txt
ovpn3-0.1.3.dist-info/LICENSE
ovpn3-0.1.3.dist-info/WHEEL
ovpn3-0.1.3.dist-info/METADATA
ovpn3-0.1.3.dist-info/RECORD
